shell_style/__init__.py
shell_style/__main__.py
shell_style/enums.py
shell_style/models.py
shell_style/ssml.py
shell_style-0.2.0.dist-info/LICENSE
shell_style-0.2.0.dist-info/METADATA
shell_style-0.2.0.dist-info/WHEEL
shell_style-0.2.0.dist-info/entry_points.txt
shell_style-0.2.0.dist-info/top_level.txt
shell_style-0.2.0.dist-info/RECORD
