Metadata-Version: 2.2
Name: shell-style
Version: 0.2.0
Summary: A terminal formatting library with 24-bit color support
Home-page: https://github.com/TheOmniOnic/shell-style
Author: TheOmniOnic
Classifier: Programming Language :: Python :: 3
Classifier: License :: OSI Approved :: GNU General Public License v3 (GPLv3)
Classifier: Operating System :: OS Independent
Classifier: Environment :: Console
Classifier: Topic :: Terminals
Requires-Python: >=3.12.0
License-File: LICENSE
Dynamic: author
Dynamic: classifier
Dynamic: description
Dynamic: description-content-type
Dynamic: home-page
Dynamic: requires-python
Dynamic: summary
